setup.py
PySemver/__init__.py
PySemver/exceptions.py
PySemver/semver.py
PySemver/semver_utils.py
Py_Semver_c.egg-info/PKG-INFO
Py_Semver_c.egg-info/SOURCES.txt
Py_Semver_c.egg-info/dependency_links.txt
Py_Semver_c.egg-info/requires.txt
Py_Semver_c.egg-info/top_level.txt