Metadata-Version: 2.1
Name: Py-Semver-c
Version: 0.1.0
Summary: A python package for semver version
Home-page: https://github.com/char-46/PySemver
Author: char46
Author-email: haosiru@h-sr.cn
License: MIT
Keywords: semver,versioning,python,package,version,versioning
Requires-Python: >=3.8
Requires-Dist: typing_extensions
